music_library_micro/MusicLibrary.py
music_library_micro/__init__.py
music_library_micro-0.1.0.dist-info/METADATA
music_library_micro-0.1.0.dist-info/WHEEL
music_library_micro-0.1.0.dist-info/licenses/LICENSE
music_library_micro-0.1.0.dist-info/RECORD
